random_forest_mc/__init__.py
random_forest_mc/forest.py
random_forest_mc/model.py
random_forest_mc/tree.py
random_forest_mc/utils.py
random_forest_mc-1.3.0.dist-info/LICENSE
random_forest_mc-1.3.0.dist-info/METADATA
random_forest_mc-1.3.0.dist-info/WHEEL
random_forest_mc-1.3.0.dist-info/RECORD
