Metadata-Version: 2.3
Name: random-forest-mc
Version: 1.3.0
Summary: This project is about use Random Forest approach using a dynamic tree selection Monte Carlo based.
License: MIT
Keywords: random forest,random,monte carlo
Author: Israel Oliveira
Author-email: prof.israel@gmail.com
Requires-Python: >=3.9.1,<3.14
Classifier: Development Status :: 5 - Production/Stable
Classifier: License :: OSI Approved :: MIT License
Classifier: Programming Language :: Python :: 3
Classifier: Programming Language :: Python :: 3.10
Classifier: Programming Language :: Python :: 3.11
Classifier: Programming Language :: Python :: 3.12
Classifier: Programming Language :: Python :: 3.13
Classifier: Programming Language :: Python :: 3.9
Classifier: Topic :: Scientific/Engineering
Classifier: Topic :: Scientific/Engineering :: Artificial Intelligence
Classifier: Topic :: Scientific/Engineering :: Human Machine Interfaces
Requires-Dist: numpy (>=1.20)
Requires-Dist: pandas (>=1.3)
Requires-Dist: tqdm (>=4.60)
Project-URL: Homepage, https://github.com/ysraell/random-forest-mc
Project-URL: Repository, https://github.com/ysraell/random-forest-mc
